README.md
setup.py
sqlpie/__init__.py
sqlpie/client.py
sqlpie/compiler.py
sqlpie/dynamic_env.py
sqlpie/exceptions.py
sqlpie/executor.py
sqlpie/model_engine.py
sqlpie/project.py
sqlpie.egg-info/PKG-INFO
sqlpie.egg-info/SOURCES.txt
sqlpie.egg-info/dependency_links.txt
sqlpie.egg-info/requires.txt
sqlpie.egg-info/top_level.txt
test/tests.py