Metadata-Version: 2.1
Name: sqlpie
Version: 0.7.5.7
Summary: Data lakes Development Framework
Home-page: UNKNOWN
Author: Omri Shuva
Author-email: omrishuva1@gmail.com
License: UNKNOWN
Platform: UNKNOWN
Classifier: Programming Language :: Python :: 3
Classifier: License :: OSI Approved :: MIT License
Classifier: Operating System :: OS Independent
